airflow_provider_dolphindb/__init__.py
airflow_provider_dolphindb/hooks/__init__.py
airflow_provider_dolphindb/hooks/dolphindb.py
airflow_provider_dolphindb/operators/__init__.py
airflow_provider_dolphindb/operators/dolphindb.py
airflow_provider_dolphindb-1.1.0.dist-info/METADATA
airflow_provider_dolphindb-1.1.0.dist-info/WHEEL
airflow_provider_dolphindb-1.1.0.dist-info/entry_points.txt
airflow_provider_dolphindb-1.1.0.dist-info/top_level.txt
airflow_provider_dolphindb-1.1.0.dist-info/RECORD
