Metadata-Version: 2.1
Name: airflow-provider-dolphindb
Version: 1.1.0
Summary: Apache Airflow DolphinDB provider containing Operators.
Home-page: https://www.dolphindb.com
Author: DolphinDB, Inc.
Author-email: support@dolphindb.com
License: Apache License 2.0
Project-URL: Source Code, https://github.com/dolphindb/airflow-provider-dolphindb
Project-URL: Homepage, https://github.com/dolphindb/airflow-provider-dolphindb
Classifier: Development Status :: 4 - Beta
Classifier: Environment :: Web Environment
Classifier: Intended Audience :: Developers
Classifier: Intended Audience :: System Administrators
Classifier: Framework :: Apache Airflow
Classifier: Framework :: Apache Airflow :: Provider
Classifier: License :: OSI Approved :: Apache Software License
Classifier: Operating System :: OS Independent
Classifier: Programming Language :: Python
Classifier: Programming Language :: Python :: 3
Classifier: Programming Language :: Python :: 3.8
Classifier: Programming Language :: Python :: 3.9
Classifier: Programming Language :: Python :: 3.10
Classifier: Topic :: System :: Monitoring
Requires-Python: >=3.8
Requires-Dist: apache-airflow (>=2.2.0)
Requires-Dist: pydolphindb
Requires-Dist: dolphindb (>=3.0.2.2)
Provides-Extra: dev
Requires-Dist: pytest ; extra == 'dev'
